easybits_module_interface/__init__.py
easybits_module_interface/_app_helpers.py
easybits_module_interface/_internal.py
easybits_module_interface/_version.py
easybits_module_interface/logger.py
easybits_module_interface/models/__init__.py
easybits_module_interface/models/base.py
easybits_module_interface/models/enum.py
easybits_module_interface/models/message.py
easybits_module_interface/models/module.py
easybits_module_interface/models/tool_chain.py
easybits_module_interface/state_machine.py
easybits_module_interface/task_execution/__init__.py
easybits_module_interface/task_execution/models.py
easybits_module_interface/task_execution/task_executor.py
easybits_module_interface/task_execution/thread_pool_executor.py
easybits_module_interface/test_clients.py
easybits_module_interface/utils.py
eb_mi-1.5.2.dist-info/METADATA
eb_mi-1.5.2.dist-info/WHEEL
eb_mi-1.5.2.dist-info/RECORD
