Metadata-Version: 2.4
Name: eb-mi
Version: 1.5.2
Summary: 
Author: Philipp Zettl
Author-email: philipp@easybits.tech
Requires-Python: >=3.10,<4.0
Classifier: Programming Language :: Python :: 3
Classifier: Programming Language :: Python :: 3.10
Classifier: Programming Language :: Python :: 3.11
Classifier: Programming Language :: Python :: 3.12
Classifier: Programming Language :: Python :: 3.13
Classifier: Programming Language :: Python :: 3.14
Requires-Dist: aio-pika (>=9.4.0,<10.0.0)
Requires-Dist: requests (>=2.31.0,<3.0.0)
Requires-Dist: sentry-sdk (>=2.29.1,<3.0.0)
